{
    "code": "1",
    "rows": [
        {
            "uid": "0",
            "name": "Camon",
            "text": "@JimQee Check it out!",
            "time": "0",
            "content": {
                "type": "1",
                "score": "22",
                "unit": "1",
                "played": "237593",
                "gameId": "1",
                "gameName": "Birds Jump",
                "comment": "185",
                "hot": "3949"
            }

        },
        {
            "uid": "0",
            "name": "Camon",
            "text": "@JimQee Check it out!",
            "time": "0",
            "content": {
                "type": "1",
                "score": "22",
                "unit": "1",
                "played": "237593",
                "gameId": "1",
                "gameName": "Birds Jump",
                "comment": "185",
                "hot": "3949"
            }

        },
        {
            "uid": "0",
            "name": "Camon",
            "text": "@JimQee Check it out!",
            "time": "0",
            "content": {
                "type": "1",
                "score": "22",
                "unit": "1",
                "played": "237593",
                "gameId": "1",
                "gameName": "Birds Jump",
                "comment": "185",
                "hot": "3949"
            }

        },
        {
            "uid": "0",
            "name": "Camon",
            "text": "@JimQee Check it out!",
            "time": "0",
            "content": {
                "type": "1",
                "score": "22",
                "unit": "1",
                "played": "237593",
                "gameId": "1",
                "gameName": "Birds Jump",
                "comment": "185",
                "hot": "3949"
            }

        },
        {
            "uid": "0",
            "name": "Camon",
            "text": "@JimQee Check it out!",
            "time": "0",
            "content": {
                "type": "1",
                "score": "22",
                "unit": "1",
                "played": "237593",
                "gameId": "1",
                "gameName": "Birds Jump",
                "comment": "185",
                "hot": "3949"
            }

        },
        {
            "uid": "0",
            "name": "Camon",
            "text": "@JimQee Check it out!",
            "time": "0",
            "content": {
                "type": "1",
                "score": "22",
                "unit": "1",
                "played": "237593",
                "gameId": "1",
                "gameName": "Birds Jump",
                "comment": "185",
                "hot": "3949"
            }

        },
        {
            "uid": "0",
            "name": "Camon",
            "text": "@JimQee Check it out!",
            "time": "0",
            "content": {
                "type": "1",
                "score": "22",
                "unit": "1",
                "played": "237593",
                "gameId": "1",
                "gameName": "Birds Jump",
                "comment": "185",
                "hot": "3949"
            }

        }
    ],
    "time": "0"
}